{"ул. Карла Либкнехта": "305001", "Красная пл.": "305000", "пр-т Вячеслава Клыкова": "305005", "пр-т Победы": "305021", "Студенческая ул.": "305040", "ул. Горького": "305000", "пр-т Хрущёва": "305038", "ул. Блинова": "305004", "пр-т Надежды Плевицкой": "305005", "Союзная ул.": "305044", "Почтовая ул.": "305000", "ул. 50 лет Октября": "305016", "ул. Дзержинского": "305000", "ул. Карла Маркса": "305004", "ул. Менделеева": "305026", "Звёздная ул.": "305003", "ул. Бойцов 9-й Дивизии": "305003", "пр-т Дружбы": "305040", "ул. Черняховского": "305018", "Школьная ул.": "305021", "ул. Косухина": "305048", "пр-т Ленинского Комсомола": "305018", "1-я Ламоновская ул.": "305018", "пр-т Анатолия Дериглазова": "305006", "ул. Щепкина": "305016", "ул. Крюкова": "305045", "ул. Радищева": "305000", "ул. Ленина": "305000", "ул. Володарского": "305000", "ул. Ватутина": "305000", "ул. Димитрова": "305000", "Магистральный пр.": "305025", "ул. Домостроителей": "305006", "ул. Павлуновского": "305016", "Хуторская ул.": "305029", "ул. Дейнеки": "305007", "ул. Льва Толстого": "305004", "ул. Челюскинцев": "305004", "Мирная ул.": "305004", "ул. Гоголя": "305004", "Московский пр.": "305004", "ул. Чапаева": "305010", "Советская ул.": "305016", "ул. Пионеров": "305001", "2-я ул. Новосёловка": "305031", "ул. Гайдара": "305001", "Институтская ул.": "305021", "ул. Чернышевского": "305016", "Запольная ул.": "305040", "Дружининская ул.": "305001", "Кавказская ул.": "305021", "1-я Воронежская ул.": "305022", "ул. Софьи Перовской": "305001", "ул. Перекальского": "305004", "ул. Пучковка": "305008", "Майский б-р": "305005", "Орловская ул.": "305008", "Чумаковская ул.": "305035", "ул. Степана Разина": "305004", "Никитская ул.": "305029", "пр-т Энтузиастов": "305040", "Сумская ул.": "305007", "ул. Генерала Григорова": "305014", "ул. Комарова": "305047", "Республиканская ул.": "305044", "Рябиновая ул.": "305014", "ул. Большевиков": "305001", "Ендовищенская ул.": "305000", "ул. Халтурина": "305004"}